{
  "en": {
    "app_title": "EACO Beginner Guide + Foreign Trade",
    "lang_name": "English",
    "hero_title": "Welcome to EACO",
    "hero_subtitle": "AI-powered community token on Solana | Min trade: $0.01",
    "ca_label": "Contract Address (CA):",
    "ca_value": "DqfoyZH96RnvZusSp3Cdncjpyp3C74ZmJzGhjmHnDHRH",
    "copy_btn": "Copy CA",
    "copied": "Copied!",
    "orb_btn": "OrbMarkets",
    "solscan_btn": "Solscan",
    "min_trade": "Minimum Trade: $0.01",
    "min_trade_desc": "Start with as little as $0.01 - perfect for beginners!",
    "wallet_section": "Step 1: Get a Wallet",
    "wallet_desc": "Download Solflare wallet - recommended for EACO. Min deposit: $0.01 equivalent in SOL.",
    "wallet_link": "https://solflare.com/",
    "wallet_link_text": "Download Solflare →",
    "security_title": "Security First",
    "sec_1": "Never share your seed phrase with anyone",
    "sec_2": "Only use official links (verify CA each time)",
    "sec_3": "Start with $0.01 minimum trade - test first",
    "sec_4": "Always double-check contract before trading",
    "tutorial_title": "Step-by-Step Guide",
    "step1_title": "Create Your Wallet",
    "step1_desc": "Download Solflare from solflare.com. Create wallet, backup 12-word seed phrase. Never share it!",
    "step2_title": "Add Funds (Min $0.01)",
    "step2_desc": "Buy SOL from any exchange (Binance, OKX, etc.). Even $0.01 equivalent in SOL is enough to start! Transfer to your Solflare wallet.",
    "step3_title": "Get EACO Tokens",
    "step3_desc": "Go to OrbMarkets or Solflare Swap. Search CA: DqfoyZH96RnvZusSp3Cdncjpyp3C74ZmJzGhjmHnDHRH. Minimum buy: just $0.01!",
    "step4_title": "Trade & Hold (Min $0.01)",
    "step4_desc": "Trade any amount from $0.01! Consider staking for up to 2x monthly consensus rewards.",
    "step5_title": "Join Community & Earn",
    "step5_desc": "Daily check-in, promotions, AI tasks. Top contributors earn airdrop eligibility + up to 2x staking multiplier!",
    "tips_title": "Pro Tips",
    "tip_1": "Minimum trade is only $0.01 - start small!",
    "tip_2": "Use Solflare Swap for best rates on Solana",
    "tip_3": "Verify CA DqfoyZH96RnvZusSp3Cdncjpyp3C74ZmJzGhjmHnDHRH before every trade",
    "tip_4": "Stake for 30/90/180/365 days → 1.1x/1.3x/1.5x/2.0x multiplier",
    "foreign_trade_title": "Foreign Trade Mode",
    "ft_min": "Minimum Trade: $0.01",
    "ft_fee": "Trading Fee: ~0.25%",
    "ft_speed": "Speed: ~1 second settlement",
    "ft_support": "24/7 Global Support",
    "footer_text": "Updated: 2026-05-30 | EACO - Min Trade $0.01 | CA: DqfoyZH96RnvZusSp3Cdncjpyp3C74ZmJzGhjmHnDHRH"
  },
  "zh": {
    "app_title": "EACO 新手指南 + 外贸交易",
    "lang_name": "中文",
    "hero_title": "欢迎来到 EACO",
    "hero_subtitle": "Solana 上的 AI 驱动社区代币 | 最低交易：$0.01",
    "ca_label": "合约地址 (CA)：",
    "ca_value": "DqfoyZH96RnvZusSp3Cdncjpyp3C74ZmJzGhjmHnDHRH",
    "copy_btn": "复制 CA",
    "copied": "已复制！",
    "orb_btn": "OrbMarkets",
    "solscan_btn": "Solscan",
    "min_trade": "最低交易：$0.01",
    "min_trade_desc": "最低只需 $0.01 即可开始交易，新手友好！",
    "wallet_section": "第1步：获取钱包",
    "wallet_desc": "下载 Solflare 钱包 — EACO 推荐钱包。最低充值：等价 $0.01 的 SOL。",
    "wallet_link": "https://solflare.com/",
    "wallet_link_text": "下载 Solflare →",
    "security_title": "安全第一",
    "sec_1": "绝不向任何人透露种子短语",
    "sec_2": "仅使用官方链接（每次核对 CA）",
    "sec_3": "从最低 $0.01 开始 — 先小额测试",
    "sec_4": "交易前务必核对合约地址",
    "tutorial_title": "分步教程",
    "step1_title": "创建钱包",
    "step1_desc": "从 solflare.com 下载 Solflare，创建钱包并安全备份12字种子短语，切勿泄露！",
    "step2_title": "充值（最低 $0.01）",
    "step2_desc": "从任何交易所（Binance、OKX等）购买 SOL。即使等价 $0.01 的 SOL 也足够开始！",
    "step3_title": "获取 EACO 代币",
    "step3_desc": "访问 OrbMarkets 或 Solflare Swap。搜索 CA：DqfoyZH96RnvZusSp3Cdncjpyp3C74ZmJzGhjmHnDHRH，最低买入仅需 $0.01！",
    "step4_title": "交易与持有（最低 $0.01）",
    "step4_desc": "最低 $0.01 即可交易！考虑锁仓获得高达 2 倍月度共识奖励。",
    "step5_title": "加入社区赚取",
    "step5_desc": "每日签到、推广、AI任务。顶级贡献者获得空投资格 + 最高 2 倍锁仓加成！",
    "tips_title": "专业提示",
    "tip_1": "最低交易仅需 $0.01 — 小额开始！",
    "tip_2": "使用 Solflare Swap 获取最佳汇率",
    "tip_3": "每次交易前核对 CA：DqfoyZH96RnvZusSp3Cdncjpyp3C74ZmJzGhjmHnDHRH",
    "tip_4": "锁仓 30/90/180/365 天 → 1.1x/1.3x/1.5x/2.0x 加成",
    "foreign_trade_title": "外贸交易模式",
    "ft_min": "最低交易：$0.01",
    "ft_fee": "交易手续费：约 0.25%",
    "ft_speed": "结算速度：约 1 秒",
    "ft_support": "24/7 全球支持",
    "footer_text": "更新日期：2026-05-30 | EACO - 最低交易 $0.01 | CA: DqfoyZH96RnvZusSp3Cdncjpyp3C74ZmJzGhjmHnDHRH"
  },
  "es": {
    "app_title": "Guía EACO + Comercio Exterior",
    "lang_name": "Español",
    "hero_title": "Bienvenido a EACO",
    "hero_subtitle": "Token comunitario con IA en Solana | Mín. trade: $0.01",
    "ca_label": "Dirección del Contrato (CA):",
    "ca_value": "DqfoyZH96RnvZusSp3Cdncjpyp3C74ZmJzGhjmHnDHRH",
    "copy_btn": "Copiar CA",
    "copied": "¡Copiado!",
    "orb_btn": "OrbMarkets",
    "solscan_btn": "Solscan",
    "min_trade": "Mín. Trade: $0.01",
    "min_trade_desc": "¡Comienza con solo $0.01 - perfecto para principiantes!",
    "wallet_section": "Paso 1: Obtén una Billetera",
    "wallet_desc": "Descarga Solflare - recomendada para EACO. Depósito mín: equivalente a $0.01 en SOL.",
    "wallet_link": "https://solflare.com/",
    "wallet_link_text": "Descargar Solflare →",
    "security_title": "Seguridad Primero",
    "sec_1": "Nunca compartas tu frase semilla",
    "sec_2": "Solo usa enlaces oficiales (verifica CA siempre)",
    "sec_3": "Empieza con mínimo $0.01 - prueba primero",
    "sec_4": "Verifica el contrato antes de cada operación",
    "tutorial_title": "Guía Paso a Paso",
    "step1_title": "Crea tu Billetera",
    "step1_desc": "Descarga Solflare de solflare.com. Crea billetera, respalda 12 palabras. ¡Nunca las compartas!",
    "step2_title": "Fondos (Mín $0.01)",
    "step2_desc": "Compra SOL en cualquier exchange. ¡Solo $0.01 equivalente en SOL es suficiente!",
    "step3_title": "Obtén EACO",
    "step3_desc": "Ve a OrbMarkets o Solflare Swap. Busca CA. ¡Mínimo de compra: solo $0.01!",
    "step4_title": "Opera y Mantén (Mín $0.01)",
    "step4_desc": "Opera desde $0.01. Considera staking para recompensas hasta 2x.",
    "step5_title": "Únete y Gana",
    "step5_desc": "Check-ins diarios, promociones, tareas IA. ¡Los mejores obtienen air rewards!",
    "tips_title": "Consejos Pro",
    "tip_1": "Mínimo de trade: solo $0.01",
    "tip_2": "Usa Solflare Swap para mejores tasas",
    "tip_3": "Verifica CA antes de cada trade",
    "tip_4": "Staking 30/90/180/365 días → 1.1x/1.3x/1.5x/2.0x",
    "foreign_trade_title": "Modo Comercio Exterior",
    "ft_min": "Mín. Trade: $0.01",
    "ft_fee": "Comisión: ~0.25%",
    "ft_speed": "Liquidación: ~1 segundo",
    "ft_support": "Soporte 24/7 Global",
    "footer_text": "Actualizado: 2026-05-30 | EACO - Mín. $0.01"
  },
  "fr": {
    "app_title": "Guide EACO + Commerce Extérieur",
    "lang_name": "Français",
    "hero_title": "Bienvenue sur EACO",
    "hero_subtitle": "Token communautaire IA sur Solana | Min. trade: $0.01",
    "ca_label": "Adresse du Contrat (CA):",
    "ca_value": "DqfoyZH96RnvZusSp3Cdncjpyp3C74ZmJzGhjmHnDHRH",
    "copy_btn": "Copier CA",
    "copied": "Copié!",
    "orb_btn": "OrbMarkets",
    "solscan_btn": "Solscan",
    "min_trade": "Min. Trade: $0.01",
    "min_trade_desc": "Commencez avec seulement $0.01 - parfait pour débutants!",
    "wallet_section": "Étape 1: Obtenir un Portefeuille",
    "wallet_desc": "Téléchargez Solflare - recommandé pour EACO. Dépôt min: équivalent $0.01 en SOL.",
    "wallet_link": "https://solflare.com/",
    "wallet_link_text": "Télécharger Solflare →",
    "security_title": "Sécurité Avant Tout",
    "sec_1": "Ne partagez jamais votre phrase seed",
    "sec_2": "Utilisez uniquement les liens officiels",
    "sec_3": "Commencez par $0.01 minimum",
    "sec_4": "Vérifiez toujours le contrat avant de trader",
    "tutorial_title": "Guide Étape par Étape",
    "step1_title": "Créer le Portefeuille",
    "step1_desc": "Téléchargez Solflare depuis solflare.com. Sauvegardez votre phrase de 12 mots.",
    "step2_title": "Approvisionner (Min $0.01)",
    "step2_desc": "Achetez SOL sur n'importe quel exchange. Même $0.01 équivalent suffit!",
    "step3_title": "Obtenir des EACO",
    "step3_desc": "OrbMarkets ou Solflare Swap. Cherchez CA. Achat minimum: seulement $0.01!",
    "step4_title": "Trader et Détenir (Min $0.01)",
    "step4_desc": "Tradez à partir de $0.01. Stakez pour des récompenses jusqu'à 2x!",
    "step5_title": "Rejoindre et Gagner",
    "step5_desc": "Check-ins quotidiens, promotions, tâches IA. Les meilleurs reçoivent des air drops!",
    "tips_title": "Conseils Pro",
    "tip_1": "Trade minimum: $0.01 seulement",
    "tip_2": "Solflare Swap pour les meilleurs taux",
    "tip_3": "Vérifiez le CA avant chaque trade",
    "tip_4": "Staking 30/90/180/365 jours → 1.1x/1.3x/1.5x/2.0x",
    "foreign_trade_title": "Mode Commerce Extérieur",
    "ft_min": "Min. Trade: $0.01",
    "ft_fee": "Frais: ~0.25%",
    "ft_speed": "Règlement: ~1 seconde",
    "ft_support": "Support 24/7 Mondial",
    "footer_text": "Mis à jour: 2026-05-30 | EACO - Min. $0.01"
  },
  "ar": {
    "app_title": "دليل EACO + التجارة الخارجية",
    "lang_name": "العربية",
    "hero_title": "مرحباً في EACO",
    "hero_subtitle": "رمز مجتمعي بالذكاء الاصطناعي على سولانا | الحد الأدنى: $0.01",
    "ca_label": "عنوان العقد (CA):",
    "ca_value": "DqfoyZH96RnvZusSp3Cdncjpyp3C74ZmJzGhjmHnDHRH",
    "copy_btn": "نسخ CA",
    "copied": "تم النسخ!",
    "orb_btn": "OrbMarkets",
    "solscan_btn": "Solscan",
    "min_trade": "الحد الأدنى: $0.01",
    "min_trade_desc": "ابدأ بـ $0.01 فقط - مثالي للمبتدئين!",
    "wallet_section": "الخطوة 1: الحصول على محفظة",
    "wallet_desc": "حمل Solflare - الموصى بها لـ EACO. الإيداع الأدنى: $0.01.",
    "wallet_link": "https://solflare.com/",
    "wallet_link_text": "تحميل Solflare ←",
    "security_title": "الأمان أولاً",
    "sec_1": "لا تشارك عبارة البذر أبداً",
    "sec_2": "استخدم الروابط الرسمية فقط",
    "sec_3": "ابدأ بـ $0.01 - جرب أولاً",
    "sec_4": "تحقق من العقد قبل كل تداول",
    "tutorial_title": "دليل خطوة بخطوة",
    "step1_title": "إنشاء محفظتك",
    "step1_desc": "حمل Solflare من solflare.com. أنشئ محفظة واحفظ الـ 12 كلمة.",
    "step2_title": "الإيداع (الأدنى $0.01)",
    "step2_desc": "اشترِ SOL من أي منصة. حتى $0.01 يكفي للبدء!",
    "step3_title": "احصل على EACO",
    "step3_desc": "اذهب إلى OrbMarkets أو Solflare Swap. الحد الأدنى للشراء: $0.01 فقط!",
    "step4_title": "التداول (الأدنى $0.01)",
    "step4_desc": "تداول من $0.01. فكر في Staking لمكافآت حتى 2x!",
    "step5_title": "انضم واكسب",
    "step5_desc": "تسجيل يومي، ترويج، مهام ذكاء اصطناعي. الأفضل يحصلون على Air Drop!",
    "tips_title": "نصائح احترافية",
    "tip_1": "الحد الأدنى للتداول: $0.01 فقط",
    "tip_2": "استخدم Solflare Swap لأفضل الأسعار",
    "tip_3": "تحقق من CA قبل كل تداول",
    "tip_4": "Staking 30/90/180/365 يوم → 1.1x/1.3x/1.5x/2.0x",
    "foreign_trade_title": "وضع التجارة الخارجية",
    "ft_min": "الحد الأدنى: $0.01",
    "ft_fee": "الرسوم: ~0.25%",
    "ft_speed": "التسوية: ~1 ثانية",
    "ft_support": "دعم 24/7 عالمي",
    "footer_text": "تحديث: 2026-05-30 | EACO - الحد الأدنى $0.01"
  },
  "ru": {
    "app_title": "EACO + Внешняя Торговля",
    "lang_name": "Русский",
    "hero_title": "Добро пожаловать в EACO",
    "hero_subtitle": "Токен сообщества с ИИ на Solana | Мин. сделка: $0.01",
    "ca_label": "Адрес контракта (CA):",
    "ca_value": "DqfoyZH96RnvZusSp3Cdncjpyp3C74ZmJzGhjmHnDHRH",
    "copy_btn": "Копировать CA",
    "copied": "Скопировано!",
    "orb_btn": "OrbMarkets",
    "solscan_btn": "Solscan",
    "min_trade": "Мин. Сделка: $0.01",
    "min_trade_desc": "Начните всего с $0.01 - идеально для новичков!",
    "wallet_section": "Шаг 1: Получите кошелёк",
    "wallet_desc": "Скачайте Solflare - рекомендованный кошелёк для EACO. Мин. депозит: $0.01 в SOL.",
    "wallet_link": "https://solflare.com/",
    "wallet_link_text": "Скачать Solflare ←",
    "security_title": "Безопасность превыше всего",
    "sec_1": "Никогда не делитесь сид-фразой",
    "sec_2": "Используйте только официальные ссылки",
    "sec_3": "Начните с минимум $0.01",
    "sec_4": "Всегда проверяйте контракт перед торговлей",
    "tutorial_title": "Пошаговое руководство",
    "step1_title": "Создайте кошелёк",
    "step1_desc": "Скачайте Solflare с solflare.com. Сохраните сид-фразу из 12 слов.",
    "step2_title": "Пополнение (Мин $0.01)",
    "step2_desc": "Купите SOL на любой бирже. Даже $0.01 эквивалент достаточно!",
    "step3_title": "Получите EACO",
    "step3_desc": "OrbMarkets или Solflare Swap. Мин. покупка: всего $0.01!",
    "step4_title": "Торговля (Мин $0.01)",
    "step4_desc": "Торгуйте от $0.01.考虑质押获得奖励高达 2x!",
    "step5_title": "Присоединяйтесь и зарабатывайте",
    "step5_desc": "Ежедневные чекины, продвижение, задания ИИ. Лучшие получают airdrop!",
    "tips_title": "Советы профи",
    "tip_1": "Мин. сделка: всего $0.01",
    "tip_2": "Solflare Swap для лучших курсов",
    "tip_3": "Проверяйте CA перед каждой сделкой",
    "tip_4": "Стейкинг 30/90/180/365 дней → 1.1x/1.3x/1.5x/2.0x",
    "foreign_trade_title": "Режим внешней торговли",
    "ft_min": "Мин. Сделка: $0.01",
    "ft_fee": "Комиссия: ~0.25%",
    "ft_speed": "Расчёты: ~1 секунда",
    "ft_support": "Поддержка 24/7 глобальная",
    "footer_text": "Обновлено: 2026-05-30 | EACO - Мин. $0.01"
  }
}